frir/__init__.py
frir/frir.py
sadi/__init__.py
sadi/mimeparse.py
sadi/sadi.py
sadi/serializers.py
sadi/utils.py
sadi-1.0.0.dist-info/METADATA
sadi-1.0.0.dist-info/WHEEL
sadi-1.0.0.dist-info/top_level.txt
sadi-1.0.0.dist-info/RECORD
