Metadata-Version: 2.4
Name: sadi
Version: 1.0.0
Summary: SADI for Python - Semantic Automated Discovery and Integration framework
Home-page: http://code.google.com/p/sadi/
Author: Jamie McCusker
Author-email: Jamie McCusker <mccusker@gmail.com>
Maintainer-email: Jamie McCusker <mccusker@gmail.com>
License: BSD-3-Clause
Project-URL: Homepage, http://code.google.com/p/sadi/
Project-URL: Repository, https://github.com/jpmccu/sadi
Project-URL: Documentation, http://code.google.com/p/sadi/
Project-URL: Issues, https://github.com/jpmccu/sadi/issues
Keywords: Webservices,SemanticWeb,RDF,Python,REST
Classifier: Development Status :: 4 - Beta
Classifier: Intended Audience :: Developers
Classifier: License :: OSI Approved :: BSD License
Classifier: Programming Language :: Python :: 3
Classifier: Programming Language :: Python :: 3.8
Classifier: Programming Language :: Python :: 3.9
Classifier: Programming Language :: Python :: 3.10
Classifier: Programming Language :: Python :: 3.11
Classifier: Programming Language :: Python :: 3.12
Classifier: Topic :: Internet :: WWW/HTTP
Classifier: Topic :: Software Development :: Libraries :: Python Modules
Classifier: Topic :: Scientific/Engineering
Requires-Python: >=3.8
Requires-Dist: rdflib>=4.0
Requires-Dist: Werkzeug
Requires-Dist: webob
Requires-Dist: python-dateutil
Requires-Dist: pytidylib
Dynamic: author
Dynamic: home-page
Dynamic: requires-python
